[
  {
    "ContainingType": "SWP391_Mentor_Booking_System_API.Controllers.AuthController",
    "Method": "Login",
    "RelativePath": "api/auth/login",
    "HttpMethod": "POST",
    "IsController": true,
    "Order": 0,
    "Parameters": [
      {
        "Name": "loginDto",
        "Type": "SWP391_Mentor_Booking_System_Data.DTO.LoginDTO",
        "IsRequired": true
      }
    ],
    "ReturnTypes": []
  },
  {
    "ContainingType": "SWP391_Mentor_Booking_System_API.Controllers.AuthController",
    "Method": "RefreshToken",
    "RelativePath": "api/auth/refresh-token",
    "HttpMethod": "POST",
    "IsController": true,
    "Order": 0,
    "Parameters": [
      {
        "Name": "token",
        "Type": "System.String",
        "IsRequired": true
      }
    ],
    "ReturnTypes": []
  },
  {
    "ContainingType": "SWP391_Mentor_Booking_System_API.Controllers.AuthController",
    "Method": "Register",
    "RelativePath": "api/auth/register",
    "HttpMethod": "POST",
    "IsController": true,
    "Order": 0,
    "Parameters": [
      {
        "Name": "registerDto",
        "Type": "SWP391_Mentor_Booking_System_Data.DTO.RegisterDTO",
        "IsRequired": true
      }
    ],
    "ReturnTypes": []
  },
  {
    "ContainingType": "SWP391_Mentor_Booking_System_API.Controllers.BookingController",
    "Method": "CreateBooking",
    "RelativePath": "api/Booking/create",
    "HttpMethod": "POST",
    "IsController": true,
    "Order": 0,
    "Parameters": [
      {
        "Name": "createBookingDto",
        "Type": "SWP391_Mentor_Booking_System_Data.DTO.BookingSlot.CreateBookingDTO",
        "IsRequired": true
      }
    ],
    "ReturnTypes": []
  },
  {
    "ContainingType": "SWP391_Mentor_Booking_System_API.Controllers.BookingController",
    "Method": "GetBookingsAsync",
    "RelativePath": "api/Booking/get-bookings",
    "HttpMethod": "GET",
    "IsController": true,
    "Order": 0,
    "Parameters": [],
    "ReturnTypes": []
  },
  {
    "ContainingType": "SWP391_Mentor_Booking_System_API.Controllers.BookingController",
    "Method": "GetBookingsByGroupId",
    "RelativePath": "api/Booking/get-bookings-by-groupId/{groupId}",
    "HttpMethod": "GET",
    "IsController": true,
    "Order": 0,
    "Parameters": [
      {
        "Name": "groupId",
        "Type": "System.String",
        "IsRequired": true
      }
    ],
    "ReturnTypes": []
  },
  {
    "ContainingType": "SWP391_Mentor_Booking_System_API.Controllers.BookingController",
    "Method": "GetBookingsByMentorSlotId",
    "RelativePath": "api/Booking/get-by-mentorslot/{mentorSlotId}",
    "HttpMethod": "GET",
    "IsController": true,
    "Order": 0,
    "Parameters": [
      {
        "Name": "mentorSlotId",
        "Type": "System.Int32",
        "IsRequired": true
      }
    ],
    "ReturnTypes": []
  },
  {
    "ContainingType": "SWP391_Mentor_Booking_System_API.Controllers.BookingController",
    "Method": "UpdateBookingStatus",
    "RelativePath": "api/Booking/update-status",
    "HttpMethod": "PUT",
    "IsController": true,
    "Order": 0,
    "Parameters": [
      {
        "Name": "updateBookingStatusDto",
        "Type": "SWP391_Mentor_Booking_System_Data.DTO.BookingSlot.UpdateBookingStatusDTO",
        "IsRequired": true
      }
    ],
    "ReturnTypes": []
  },
  {
    "ContainingType": "SWP391_Mentor_Booking_System_API.Controllers.FeedbackController",
    "Method": "GetFeedbacks",
    "RelativePath": "api/Feedback/get-feedbacks",
    "HttpMethod": "GET",
    "IsController": true,
    "Order": 0,
    "Parameters": [],
    "ReturnTypes": []
  },
  {
    "ContainingType": "SWP391_Mentor_Booking_System_API.Controllers.FeedbackController",
    "Method": "SubmitFeedback",
    "RelativePath": "api/Feedback/submit",
    "HttpMethod": "POST",
    "IsController": true,
    "Order": 0,
    "Parameters": [
      {
        "Name": "feedbackDto",
        "Type": "SWP391_Mentor_Booking_System_Data.DTO.FeedBack.FeedbackRequestDTO",
        "IsRequired": true
      }
    ],
    "ReturnTypes": []
  },
  {
    "ContainingType": "SWP391_Mentor_Booking_System_API.Controllers.GroupController",
    "Method": "AddMember",
    "RelativePath": "api/Group/add-member",
    "HttpMethod": "PUT",
    "IsController": true,
    "Order": 0,
    "Parameters": [
      {
        "Name": "addMemberDto",
        "Type": "SWP391_Mentor_Booking_System_Data.DTO.Group.AddMemberDTO",
        "IsRequired": true
      }
    ],
    "ReturnTypes": []
  },
  {
    "ContainingType": "SWP391_Mentor_Booking_System_API.Controllers.GroupController",
    "Method": "GetAllGroups",
    "RelativePath": "api/Group/all",
    "HttpMethod": "GET",
    "IsController": true,
    "Order": 0,
    "Parameters": [],
    "ReturnTypes": []
  },
  {
    "ContainingType": "SWP391_Mentor_Booking_System_API.Controllers.GroupController",
    "Method": "CreateGroup",
    "RelativePath": "api/Group/create",
    "HttpMethod": "POST",
    "IsController": true,
    "Order": 0,
    "Parameters": [
      {
        "Name": "createGroupDto",
        "Type": "SWP391_Mentor_Booking_System_Data.DTO.Group.CreateGroupDTO",
        "IsRequired": true
      }
    ],
    "ReturnTypes": []
  },
  {
    "ContainingType": "SWP391_Mentor_Booking_System_API.Controllers.GroupController",
    "Method": "DeleteMember",
    "RelativePath": "api/Group/delete-member",
    "HttpMethod": "PUT",
    "IsController": true,
    "Order": 0,
    "Parameters": [
      {
        "Name": "studentId",
        "Type": "System.String",
        "IsRequired": false
      }
    ],
    "ReturnTypes": []
  },
  {
    "ContainingType": "SWP391_Mentor_Booking_System_API.Controllers.GroupController",
    "Method": "DeleteGroup",
    "RelativePath": "api/Group/delete/{id}",
    "HttpMethod": "DELETE",
    "IsController": true,
    "Order": 0,
    "Parameters": [
      {
        "Name": "id",
        "Type": "System.String",
        "IsRequired": true
      }
    ],
    "ReturnTypes": []
  },
  {
    "ContainingType": "SWP391_Mentor_Booking_System_API.Controllers.GroupController",
    "Method": "GetMembers",
    "RelativePath": "api/Group/get-members/{groupId}",
    "HttpMethod": "GET",
    "IsController": true,
    "Order": 0,
    "Parameters": [
      {
        "Name": "groupId",
        "Type": "System.String",
        "IsRequired": true
      }
    ],
    "ReturnTypes": []
  },
  {
    "ContainingType": "SWP391_Mentor_Booking_System_API.Controllers.GroupController",
    "Method": "GetGroupById",
    "RelativePath": "api/Group/get/{id}",
    "HttpMethod": "GET",
    "IsController": true,
    "Order": 0,
    "Parameters": [
      {
        "Name": "id",
        "Type": "System.String",
        "IsRequired": true
      }
    ],
    "ReturnTypes": []
  },
  {
    "ContainingType": "SWP391_Mentor_Booking_System_API.Controllers.GroupController",
    "Method": "LeaveGroup",
    "RelativePath": "api/Group/leave-group",
    "HttpMethod": "PUT",
    "IsController": true,
    "Order": 0,
    "Parameters": [
      {
        "Name": "studentId",
        "Type": "System.String",
        "IsRequired": false
      }
    ],
    "ReturnTypes": []
  },
  {
    "ContainingType": "SWP391_Mentor_Booking_System_API.Controllers.GroupController",
    "Method": "UpdateGroup",
    "RelativePath": "api/Group/update",
    "HttpMethod": "PUT",
    "IsController": true,
    "Order": 0,
    "Parameters": [
      {
        "Name": "updateGroupDto",
        "Type": "SWP391_Mentor_Booking_System_Data.DTO.Group.UpdateGroupDTO",
        "IsRequired": true
      }
    ],
    "ReturnTypes": []
  },
  {
    "ContainingType": "SWP391_Mentor_Booking_System_API.Controllers.GroupController",
    "Method": "UpdateProgress",
    "RelativePath": "api/Group/update-progress",
    "HttpMethod": "PUT",
    "IsController": true,
    "Order": 0,
    "Parameters": [
      {
        "Name": "updateProgressDto",
        "Type": "SWP391_Mentor_Booking_System_Data.DTO.Group.UpdateProgressDTO",
        "IsRequired": true
      }
    ],
    "ReturnTypes": []
  },
  {
    "ContainingType": "SWP391_Mentor_Booking_System_API.Controllers.GroupController",
    "Method": "UpdateStatus",
    "RelativePath": "api/Group/update-status",
    "HttpMethod": "PUT",
    "IsController": true,
    "Order": 0,
    "Parameters": [
      {
        "Name": "dto",
        "Type": "SWP391_Mentor_Booking_System_Data.DTO.Group.UpdateStatusGroupDTO",
        "IsRequired": true
      }
    ],
    "ReturnTypes": []
  },
  {
    "ContainingType": "SWP391_Mentor_Booking_System_API.Controllers.MentorController",
    "Method": "GetMentorById",
    "RelativePath": "api/Mentor/{id}",
    "HttpMethod": "GET",
    "IsController": true,
    "Order": 0,
    "Parameters": [
      {
        "Name": "id",
        "Type": "System.String",
        "IsRequired": true
      }
    ],
    "ReturnTypes": []
  },
  {
    "ContainingType": "SWP391_Mentor_Booking_System_API.Controllers.MentorController",
    "Method": "GetAllMentors",
    "RelativePath": "api/Mentor/all",
    "HttpMethod": "GET",
    "IsController": true,
    "Order": 0,
    "Parameters": [],
    "ReturnTypes": []
  },
  {
    "ContainingType": "SWP391_Mentor_Booking_System_API.Controllers.MentorController",
    "Method": "ChangeApplyStatus",
    "RelativePath": "api/Mentor/change-apply-status/{mentorId}",
    "HttpMethod": "PUT",
    "IsController": true,
    "Order": 0,
    "Parameters": [
      {
        "Name": "mentorId",
        "Type": "System.String",
        "IsRequired": true
      }
    ],
    "ReturnTypes": []
  },
  {
    "ContainingType": "SWP391_Mentor_Booking_System_API.Controllers.MentorController",
    "Method": "DeleteMentor",
    "RelativePath": "api/Mentor/delete/{id}",
    "HttpMethod": "DELETE",
    "IsController": true,
    "Order": 0,
    "Parameters": [
      {
        "Name": "id",
        "Type": "System.String",
        "IsRequired": true
      }
    ],
    "ReturnTypes": []
  },
  {
    "ContainingType": "SWP391_Mentor_Booking_System_API.Controllers.MentorSlotController",
    "Method": "GetAllMentorSlots",
    "RelativePath": "api/MentorSlot/all",
    "HttpMethod": "GET",
    "IsController": true,
    "Order": 0,
    "Parameters": [],
    "ReturnTypes": []
  },
  {
    "ContainingType": "SWP391_Mentor_Booking_System_API.Controllers.MentorSlotController",
    "Method": "CreateMentorSlot",
    "RelativePath": "api/MentorSlot/create",
    "HttpMethod": "POST",
    "IsController": true,
    "Order": 0,
    "Parameters": [
      {
        "Name": "createMentorSlotDto",
        "Type": "SWP391_Mentor_Booking_System_Data.DTO.MentorSlot.CreateMentorSlotDTO",
        "IsRequired": true
      }
    ],
    "ReturnTypes": []
  },
  {
    "ContainingType": "SWP391_Mentor_Booking_System_API.Controllers.MentorSlotController",
    "Method": "DeleteMentorSlot",
    "RelativePath": "api/MentorSlot/delete/{id}",
    "HttpMethod": "DELETE",
    "IsController": true,
    "Order": 0,
    "Parameters": [
      {
        "Name": "id",
        "Type": "System.Int32",
        "IsRequired": true
      }
    ],
    "ReturnTypes": []
  },
  {
    "ContainingType": "SWP391_Mentor_Booking_System_API.Controllers.MentorSlotController",
    "Method": "GetMentorSlotById",
    "RelativePath": "api/MentorSlot/get-by-id/{id}",
    "HttpMethod": "GET",
    "IsController": true,
    "Order": 0,
    "Parameters": [
      {
        "Name": "id",
        "Type": "System.Int32",
        "IsRequired": true
      }
    ],
    "ReturnTypes": []
  },
  {
    "ContainingType": "SWP391_Mentor_Booking_System_API.Controllers.MentorSlotController",
    "Method": "GetMentorSlotsByMentorId",
    "RelativePath": "api/MentorSlot/get-by-mentor-id/{mentorId}",
    "HttpMethod": "GET",
    "IsController": true,
    "Order": 0,
    "Parameters": [
      {
        "Name": "mentorId",
        "Type": "System.String",
        "IsRequired": true
      }
    ],
    "ReturnTypes": []
  },
  {
    "ContainingType": "SWP391_Mentor_Booking_System_API.Controllers.MentorSlotController",
    "Method": "GetMentorAppointmentsByMentorId",
    "RelativePath": "api/MentorSlot/get-mentor-appointments-by-mentor-id/{mentorId}",
    "HttpMethod": "GET",
    "IsController": true,
    "Order": 0,
    "Parameters": [
      {
        "Name": "mentorId",
        "Type": "System.String",
        "IsRequired": true
      }
    ],
    "ReturnTypes": []
  },
  {
    "ContainingType": "SWP391_Mentor_Booking_System_API.Controllers.MentorSlotController",
    "Method": "UpdateMentorSlot",
    "RelativePath": "api/MentorSlot/update",
    "HttpMethod": "PUT",
    "IsController": true,
    "Order": 0,
    "Parameters": [
      {
        "Name": "updateMentorSlotDto",
        "Type": "SWP391_Mentor_Booking_System_Data.DTO.MentorSlot.UpdateMentorSlotDTO",
        "IsRequired": true
      }
    ],
    "ReturnTypes": []
  },
  {
    "ContainingType": "SWP391_Mentor_Booking_System_API.Controllers.RequestToMoveClassController",
    "Method": "CreateRequestToMoveClass",
    "RelativePath": "api/RequestToMoveClass/create",
    "HttpMethod": "POST",
    "IsController": true,
    "Order": 0,
    "Parameters": [
      {
        "Name": "dto",
        "Type": "SWP391_Mentor_Booking_System_Data.DTO.RequestToMoveClass.CreateRequestToMoveClassDTO",
        "IsRequired": true
      }
    ],
    "ReturnTypes": []
  },
  {
    "ContainingType": "SWP391_Mentor_Booking_System_API.Controllers.RequestToMoveClassController",
    "Method": "GetRequestToMoveClasses",
    "RelativePath": "api/RequestToMoveClass/get-all",
    "HttpMethod": "GET",
    "IsController": true,
    "Order": 0,
    "Parameters": [],
    "ReturnTypes": []
  },
  {
    "ContainingType": "SWP391_Mentor_Booking_System_API.Controllers.RequestToMoveClassController",
    "Method": "UpdateRequestToMoveClass",
    "RelativePath": "api/RequestToMoveClass/update",
    "HttpMethod": "PUT",
    "IsController": true,
    "Order": 0,
    "Parameters": [
      {
        "Name": "dto",
        "Type": "SWP391_Mentor_Booking_System_Data.DTO.RequestToMoveClass.UpdateRequestToMoveClassDTO",
        "IsRequired": true
      }
    ],
    "ReturnTypes": []
  },
  {
    "ContainingType": "SWP391_Mentor_Booking_System_API.Controllers.SemesterController",
    "Method": "GetAllSemesters",
    "RelativePath": "api/Semester/all",
    "HttpMethod": "GET",
    "IsController": true,
    "Order": 0,
    "Parameters": [],
    "ReturnTypes": []
  },
  {
    "ContainingType": "SWP391_Mentor_Booking_System_API.Controllers.SemesterController",
    "Method": "CreateSemester",
    "RelativePath": "api/Semester/create",
    "HttpMethod": "POST",
    "IsController": true,
    "Order": 0,
    "Parameters": [
      {
        "Name": "createSemesterDto",
        "Type": "SWP391_Mentor_Booking_System_Data.DTO.Semester.CreateSemesterDTO",
        "IsRequired": true
      }
    ],
    "ReturnTypes": []
  },
  {
    "ContainingType": "SWP391_Mentor_Booking_System_API.Controllers.SemesterController",
    "Method": "DeleteSemester",
    "RelativePath": "api/Semester/delete/{id}",
    "HttpMethod": "DELETE",
    "IsController": true,
    "Order": 0,
    "Parameters": [
      {
        "Name": "id",
        "Type": "System.Int32",
        "IsRequired": true
      }
    ],
    "ReturnTypes": []
  },
  {
    "ContainingType": "SWP391_Mentor_Booking_System_API.Controllers.SemesterController",
    "Method": "GetSemesterById",
    "RelativePath": "api/Semester/get/{id}",
    "HttpMethod": "GET",
    "IsController": true,
    "Order": 0,
    "Parameters": [
      {
        "Name": "id",
        "Type": "System.Int32",
        "IsRequired": true
      }
    ],
    "ReturnTypes": []
  },
  {
    "ContainingType": "SWP391_Mentor_Booking_System_API.Controllers.SemesterController",
    "Method": "UpdateSemester",
    "RelativePath": "api/Semester/update",
    "HttpMethod": "PUT",
    "IsController": true,
    "Order": 0,
    "Parameters": [
      {
        "Name": "updateSemesterDto",
        "Type": "SWP391_Mentor_Booking_System_Data.DTO.Semester.UpdateSemesterDTO",
        "IsRequired": true
      }
    ],
    "ReturnTypes": []
  },
  {
    "ContainingType": "SWP391_Mentor_Booking_System_API.Controllers.SkillsController",
    "Method": "GetSkillById",
    "RelativePath": "api/Skills/{id}",
    "HttpMethod": "GET",
    "IsController": true,
    "Order": 0,
    "Parameters": [
      {
        "Name": "id",
        "Type": "System.Int32",
        "IsRequired": true
      }
    ],
    "ReturnTypes": []
  },
  {
    "ContainingType": "SWP391_Mentor_Booking_System_API.Controllers.SkillsController",
    "Method": "AddMentorSkill",
    "RelativePath": "api/Skills/addskill",
    "HttpMethod": "POST",
    "IsController": true,
    "Order": 0,
    "Parameters": [
      {
        "Name": "dto",
        "Type": "SWP391_Mentor_Booking_System_Data.DTO.Skill.AddMentorSkillDTO",
        "IsRequired": true
      }
    ],
    "ReturnTypes": []
  },
  {
    "ContainingType": "SWP391_Mentor_Booking_System_API.Controllers.SkillsController",
    "Method": "GetAllSkills",
    "RelativePath": "api/Skills/all",
    "HttpMethod": "GET",
    "IsController": true,
    "Order": 0,
    "Parameters": [],
    "ReturnTypes": []
  },
  {
    "ContainingType": "SWP391_Mentor_Booking_System_API.Controllers.SkillsController",
    "Method": "AddSkill",
    "RelativePath": "api/Skills/create",
    "HttpMethod": "POST",
    "IsController": true,
    "Order": 0,
    "Parameters": [
      {
        "Name": "createskillDto",
        "Type": "SWP391_Mentor_Booking_System_Data.DTO.Skill.CreateSkillDTO",
        "IsRequired": true
      }
    ],
    "ReturnTypes": []
  },
  {
    "ContainingType": "SWP391_Mentor_Booking_System_API.Controllers.SkillsController",
    "Method": "DeleteSkill",
    "RelativePath": "api/Skills/delete/{id}",
    "HttpMethod": "DELETE",
    "IsController": true,
    "Order": 0,
    "Parameters": [
      {
        "Name": "id",
        "Type": "System.Int32",
        "IsRequired": true
      }
    ],
    "ReturnTypes": []
  },
  {
    "ContainingType": "SWP391_Mentor_Booking_System_API.Controllers.SkillsController",
    "Method": "GetMentorSkillsByMentorId",
    "RelativePath": "api/Skills/mentorskill/{mentorId}",
    "HttpMethod": "GET",
    "IsController": true,
    "Order": 0,
    "Parameters": [
      {
        "Name": "mentorId",
        "Type": "System.String",
        "IsRequired": true
      }
    ],
    "ReturnTypes": []
  },
  {
    "ContainingType": "SWP391_Mentor_Booking_System_API.Controllers.SkillsController",
    "Method": "DeleteMentorSkill",
    "RelativePath": "api/Skills/mentorskill/delete/{mentorSkillId}",
    "HttpMethod": "DELETE",
    "IsController": true,
    "Order": 0,
    "Parameters": [
      {
        "Name": "mentorSkillId",
        "Type": "System.Int32",
        "IsRequired": true
      }
    ],
    "ReturnTypes": []
  },
  {
    "ContainingType": "SWP391_Mentor_Booking_System_API.Controllers.SkillsController",
    "Method": "UpdateSkill",
    "RelativePath": "api/Skills/update",
    "HttpMethod": "PUT",
    "IsController": true,
    "Order": 0,
    "Parameters": [
      {
        "Name": "updateskillDto",
        "Type": "SWP391_Mentor_Booking_System_Data.DTO.Skill.UpdateSkillDTO",
        "IsRequired": true
      }
    ],
    "ReturnTypes": []
  },
  {
    "ContainingType": "SWP391_Mentor_Booking_System_API.Controllers.StudentController",
    "Method": "GetStudentById",
    "RelativePath": "api/Student/{id}",
    "HttpMethod": "GET",
    "IsController": true,
    "Order": 0,
    "Parameters": [
      {
        "Name": "id",
        "Type": "System.String",
        "IsRequired": true
      }
    ],
    "ReturnTypes": []
  },
  {
    "ContainingType": "SWP391_Mentor_Booking_System_API.Controllers.StudentController",
    "Method": "GetAllStudents",
    "RelativePath": "api/Student/all",
    "HttpMethod": "GET",
    "IsController": true,
    "Order": 0,
    "Parameters": [],
    "ReturnTypes": []
  },
  {
    "ContainingType": "SWP391_Mentor_Booking_System_API.Controllers.StudentController",
    "Method": "DeleteStudent",
    "RelativePath": "api/Student/delete/{id}",
    "HttpMethod": "DELETE",
    "IsController": true,
    "Order": 0,
    "Parameters": [
      {
        "Name": "id",
        "Type": "System.String",
        "IsRequired": true
      }
    ],
    "ReturnTypes": []
  },
  {
    "ContainingType": "SWP391_Mentor_Booking_System_API.Controllers.SwpClassController",
    "Method": "GetAllClasses",
    "RelativePath": "api/SwpClass/all",
    "HttpMethod": "GET",
    "IsController": true,
    "Order": 0,
    "Parameters": [],
    "ReturnTypes": []
  },
  {
    "ContainingType": "SWP391_Mentor_Booking_System_API.Controllers.SwpClassController",
    "Method": "CreateClass",
    "RelativePath": "api/SwpClass/create",
    "HttpMethod": "POST",
    "IsController": true,
    "Order": 0,
    "Parameters": [
      {
        "Name": "createSwpClassDto",
        "Type": "SWP391_Mentor_Booking_System_Data.DTO.SwpClass.CreateSwpClassDTO",
        "IsRequired": true
      }
    ],
    "ReturnTypes": []
  },
  {
    "ContainingType": "SWP391_Mentor_Booking_System_API.Controllers.SwpClassController",
    "Method": "DeleteClass",
    "RelativePath": "api/SwpClass/delete/{id}",
    "HttpMethod": "DELETE",
    "IsController": true,
    "Order": 0,
    "Parameters": [
      {
        "Name": "id",
        "Type": "System.Int32",
        "IsRequired": true
      }
    ],
    "ReturnTypes": []
  },
  {
    "ContainingType": "SWP391_Mentor_Booking_System_API.Controllers.SwpClassController",
    "Method": "GetClassById",
    "RelativePath": "api/SwpClass/get/{id}",
    "HttpMethod": "GET",
    "IsController": true,
    "Order": 0,
    "Parameters": [
      {
        "Name": "id",
        "Type": "System.Int32",
        "IsRequired": true
      }
    ],
    "ReturnTypes": []
  },
  {
    "ContainingType": "SWP391_Mentor_Booking_System_API.Controllers.SwpClassController",
    "Method": "UpdateClassById",
    "RelativePath": "api/SwpClass/update/{id}",
    "HttpMethod": "PUT",
    "IsController": true,
    "Order": 0,
    "Parameters": [
      {
        "Name": "id",
        "Type": "System.Int32",
        "IsRequired": true
      },
      {
        "Name": "updateSwpClassDto",
        "Type": "SWP391_Mentor_Booking_System_Data.DTO.SwpClass.UpdateSwpClassDTO",
        "IsRequired": true
      }
    ],
    "ReturnTypes": []
  },
  {
    "ContainingType": "SWP391_Mentor_Booking_System_API.Controllers.TopicController",
    "Method": "GetAllTopics",
    "RelativePath": "api/Topic/all",
    "HttpMethod": "GET",
    "IsController": true,
    "Order": 0,
    "Parameters": [],
    "ReturnTypes": []
  },
  {
    "ContainingType": "SWP391_Mentor_Booking_System_API.Controllers.TopicController",
    "Method": "CreateTopic",
    "RelativePath": "api/Topic/create",
    "HttpMethod": "POST",
    "IsController": true,
    "Order": 0,
    "Parameters": [
      {
        "Name": "createTopicDto",
        "Type": "SWP391_Mentor_Booking_System_Data.DTO.Topic.CreateTopicDTO",
        "IsRequired": true
      }
    ],
    "ReturnTypes": []
  },
  {
    "ContainingType": "SWP391_Mentor_Booking_System_API.Controllers.TopicController",
    "Method": "DeleteTopic",
    "RelativePath": "api/Topic/delete/{id}",
    "HttpMethod": "DELETE",
    "IsController": true,
    "Order": 0,
    "Parameters": [
      {
        "Name": "id",
        "Type": "System.Int32",
        "IsRequired": true
      }
    ],
    "ReturnTypes": []
  },
  {
    "ContainingType": "SWP391_Mentor_Booking_System_API.Controllers.TopicController",
    "Method": "GetTopicById",
    "RelativePath": "api/Topic/get/{id}",
    "HttpMethod": "GET",
    "IsController": true,
    "Order": 0,
    "Parameters": [
      {
        "Name": "id",
        "Type": "System.Int32",
        "IsRequired": true
      }
    ],
    "ReturnTypes": []
  },
  {
    "ContainingType": "SWP391_Mentor_Booking_System_API.Controllers.TopicController",
    "Method": "UpdateTopic",
    "RelativePath": "api/Topic/update",
    "HttpMethod": "PUT",
    "IsController": true,
    "Order": 0,
    "Parameters": [
      {
        "Name": "updateTopicDto",
        "Type": "SWP391_Mentor_Booking_System_Data.DTO.Topic.UpdateTopicDTO",
        "IsRequired": true
      }
    ],
    "ReturnTypes": []
  },
  {
    "ContainingType": "SWP391_Mentor_Booking_System_API.Controllers.TransactionController",
    "Method": "GetTransactionsByGroupIdAsync",
    "RelativePath": "api/Transaction/get-transactions-by-groupId/{groupId}",
    "HttpMethod": "GET",
    "IsController": true,
    "Order": 0,
    "Parameters": [
      {
        "Name": "groupId",
        "Type": "System.String",
        "IsRequired": true
      }
    ],
    "ReturnTypes": [
      {
        "Type": "System.Collections.Generic.List\u00601[[SWP391_Mentor_Booking_System_Data.DTO.Transaction.TransactionDTO, SWP391_Mentor_Booking_System_Data, Version=1.0.0.0, Culture=neutral, PublicKeyToken=null]]",
        "MediaTypes": [
          "text/plain",
          "application/json",
          "text/json"
        ],
        "StatusCode": 200
      }
    ]
  },
  {
    "ContainingType": "SWP391_Mentor_Booking_System_API.Controllers.TransactionController",
    "Method": "GetTransactionsByMentorId",
    "RelativePath": "api/Transaction/get-transactions-by-mentorId/{mentorId}",
    "HttpMethod": "GET",
    "IsController": true,
    "Order": 0,
    "Parameters": [
      {
        "Name": "mentorId",
        "Type": "System.String",
        "IsRequired": true
      }
    ],
    "ReturnTypes": [
      {
        "Type": "System.Collections.Generic.List\u00601[[SWP391_Mentor_Booking_System_Data.DTO.Transaction.TransactionDTO, SWP391_Mentor_Booking_System_Data, Version=1.0.0.0, Culture=neutral, PublicKeyToken=null]]",
        "MediaTypes": [
          "text/plain",
          "application/json",
          "text/json"
        ],
        "StatusCode": 200
      }
    ]
  },
  {
    "ContainingType": "SWP391_Mentor_Booking_System_API.Controllers.UserController",
    "Method": "ChangePassword",
    "RelativePath": "api/User/change-password",
    "HttpMethod": "PUT",
    "IsController": true,
    "Order": 0,
    "Parameters": [
      {
        "Name": "changePassDto",
        "Type": "SWP391_Mentor_Booking_System_Data.DTO.ChangePassDTO",
        "IsRequired": true
      }
    ],
    "ReturnTypes": []
  },
  {
    "ContainingType": "SWP391_Mentor_Booking_System_API.Controllers.UserController",
    "Method": "GenerateOtp",
    "RelativePath": "api/User/generate-otp",
    "HttpMethod": "POST",
    "IsController": true,
    "Order": 0,
    "Parameters": [
      {
        "Name": "emailRequest",
        "Type": "SWP391_Mentor_Booking_System_API.Controllers.EmailRequest",
        "IsRequired": true
      }
    ],
    "ReturnTypes": []
  },
  {
    "ContainingType": "SWP391_Mentor_Booking_System_API.Controllers.UserController",
    "Method": "SetNewPassword",
    "RelativePath": "api/User/set-new-password",
    "HttpMethod": "POST",
    "IsController": true,
    "Order": 0,
    "Parameters": [
      {
        "Name": "dto",
        "Type": "SWP391_Mentor_Booking_System_Data.DTO.SetNewPasswordDTO",
        "IsRequired": true
      }
    ],
    "ReturnTypes": []
  },
  {
    "ContainingType": "SWP391_Mentor_Booking_System_API.Controllers.UserController",
    "Method": "UpdateUser",
    "RelativePath": "api/User/update-user",
    "HttpMethod": "PUT",
    "IsController": true,
    "Order": 0,
    "Parameters": [
      {
        "Name": "updateUserDto",
        "Type": "SWP391_Mentor_Booking_System_Data.DTO.UpdateUserDTO",
        "IsRequired": true
      }
    ],
    "ReturnTypes": []
  },
  {
    "ContainingType": "SWP391_Mentor_Booking_System_API.Controllers.UserController",
    "Method": "ValidateOtp",
    "RelativePath": "api/User/validate-otp",
    "HttpMethod": "POST",
    "IsController": true,
    "Order": 0,
    "Parameters": [
      {
        "Name": "otpRequest",
        "Type": "SWP391_Mentor_Booking_System_API.Controllers.OtpRequest",
        "IsRequired": true
      }
    ],
    "ReturnTypes": []
  }
]